agentmatrix/__init__.py
agentmatrix/cli_runner.py
agentmatrix/agents/__init__.py
agentmatrix/agents/base.py
agentmatrix/agents/claude_coder.py
agentmatrix/agents/data_crawler.py
agentmatrix/agents/micro_agent.py
agentmatrix/agents/post_office.py
agentmatrix/agents/report_writer.py
agentmatrix/agents/secretary.py
agentmatrix/agents/stateful.py
agentmatrix/agents/user_proxy.py
agentmatrix/agents/worker.py
agentmatrix/backends/__init__.py
agentmatrix/backends/llm_client.py
agentmatrix/backends/mock_llm.py
agentmatrix/core/__init__.py
agentmatrix/core/action.py
agentmatrix/core/cerebellum.py
agentmatrix/core/events.py
agentmatrix/core/loader.py
agentmatrix/core/loader_v1.py
agentmatrix/core/log_util.py
agentmatrix/core/message.py
agentmatrix/core/prompt_engine.py
agentmatrix/core/runtime.py
agentmatrix/core/session.py
agentmatrix/core/browser/bing.py
agentmatrix/core/browser/browser_adapter.py
agentmatrix/core/browser/browser_common.py
agentmatrix/core/browser/drission_page_adapter.py
agentmatrix/core/browser/google.py
agentmatrix/db/__init__.py
agentmatrix/db/database.py
agentmatrix/db/vector_db.py
agentmatrix/profiles/claude_coder.yml
agentmatrix/profiles/mark.yml
agentmatrix/profiles/planner.yml
agentmatrix/profiles/tom_the_data_crawler.yml
agentmatrix/profiles/user_proxy.yml
agentmatrix/profiles/prompts/base.txt
agentmatrix/profiles/prompts/base_v1.txt
agentmatrix/profiles/prompts/base_v2.txt
agentmatrix/skills/__init__.py
agentmatrix/skills/crawler_helpers.py
agentmatrix/skills/data_crawler.py
agentmatrix/skills/deep_researcher.py
agentmatrix/skills/deep_researcher_helper.py
agentmatrix/skills/filesystem.py
agentmatrix/skills/markdown_editor.py
agentmatrix/skills/notebook.py
agentmatrix/skills/parser_utils.py
agentmatrix/skills/project_management.py
agentmatrix/skills/report_writer.py
agentmatrix/skills/report_writer_utils.py
agentmatrix/skills/search_results_parser.py
agentmatrix/skills/search_tool.py
agentmatrix/skills/skill_helpers.py
matrix_for_agents-0.1.5.dist-info/licenses/LICENSE
matrix_for_agents-0.1.5.dist-info/METADATA
matrix_for_agents-0.1.5.dist-info/WHEEL
matrix_for_agents-0.1.5.dist-info/top_level.txt
matrix_for_agents-0.1.5.dist-info/RECORD
