Metadata-Version: 2.4
Name: matrix-for-agents
Version: 0.1.5
Summary: An intelligent agent framework with pluggable skills and LLM integrations
Author: Agent-Matrix Contributors
License: Apache-2.0
Project-URL: Homepage, https://github.com/webdkt/agentmatrix
Project-URL: Documentation, https://github.com/webdkt/agentmatrix/docs
Project-URL: Repository, https://github.com/webdkt/agentmatrix
Project-URL: Issues, https://github.com/webdkt/agentmatrix/issues
Keywords: agents,ai,llm,framework,multi-agent
Classifier: Development Status :: 3 - Alpha
Classifier: Intended Audience :: Developers
Classifier: Topic :: Software Development :: Libraries :: Application Frameworks
Classifier: License :: OSI Approved :: Apache Software License
Classifier: Programming Language :: Python :: 3
Classifier: Programming Language :: Python :: 3.12
Classifier: Programming Language :: Python :: 3.13
Requires-Python: >=3.12
License-File: LICENSE
Requires-Dist: fastapi>=0.100.0
Requires-Dist: uvicorn>=0.23.0
Requires-Dist: websockets>=11.0
Requires-Dist: pyyaml>=6.0
Requires-Dist: python-dotenv>=1.0.0
Requires-Dist: requests>=2.31.0
Requires-Dist: aioconsole>=0.6.0
Requires-Dist: aiohttp>=3.8.0
Requires-Dist: Jinja2>=3.1.0
Requires-Dist: chromadb>=0.4.0
Requires-Dist: sentence-transformers>=2.2.0
Requires-Dist: trafilatura>=1.6.0
Requires-Dist: DrissionPage>=4.0.0
Requires-Dist: beautifulsoup4>=4.12.0
Requires-Dist: marker-pdf==1.8.0
Requires-Dist: PyMuPDF>=1.23.0
Requires-Dist: libtmux>=0.52.0
Provides-Extra: dev
Requires-Dist: pytest>=7.0; extra == "dev"
Requires-Dist: black>=23.0; extra == "dev"
Requires-Dist: flake8>=6.0; extra == "dev"
Requires-Dist: mypy>=1.0; extra == "dev"
Dynamic: license-file
